c2p2/__init__.py
c2p2/app.py
c2p2/context.py
c2p2/models.py
c2p2/settings.py
c2p2/handlers/__init__.py
c2p2/handlers/base.py
c2p2/handlers/github.py
c2p2/handlers/pages.py
c2p2/tests/__init__.py
c2p2/tests/test_extensions.py
c2p2/tests/test_handlers.py
c2p2/tests/test_models.py
c2p2/utils/__init__.py
c2p2/utils/github.py
c2p2/utils/md.py
c2p2/utils/path.py
c2p2-0.1.3.dist-info/LICENSE
c2p2-0.1.3.dist-info/METADATA
c2p2-0.1.3.dist-info/WHEEL
c2p2-0.1.3.dist-info/top_level.txt
c2p2-0.1.3.dist-info/RECORD
