Metadata-Version: 2.1
Name: c2p2
Version: 0.1.3
Summary: Code Commit Push Publish engine.
Home-page: https://github.com/nanvel/c2p2
Author: Oleksandr Polieno
Author-email: polyenoom@gmail.com
License: The MIT License
Keywords: tornado,github,blog,publish
Platform: OS Independent
License-File: LICENSE
